tasq_client/__init__.py
tasq_client/check_type.py
tasq_client/check_type_test.py
tasq_client/client.py
tasq_client_python-0.1.17.dist-info/METADATA
tasq_client_python-0.1.17.dist-info/WHEEL
tasq_client_python-0.1.17.dist-info/top_level.txt
tasq_client_python-0.1.17.dist-info/RECORD
