Metadata-Version: 2.1
Name: tasq-client-python
Version: 0.1.17
Summary: UNKNOWN
Home-page: UNKNOWN
License: UNKNOWN
Platform: UNKNOWN
Requires-Dist: requests
